countnclear/__init__.py
countnclear/counter.py
tests/__init__.py
tests/test_counter.py
countnclear-1.0.0.dist-info/LICENSE
countnclear-1.0.0.dist-info/METADATA
countnclear-1.0.0.dist-info/WHEEL
countnclear-1.0.0.dist-info/top_level.txt
countnclear-1.0.0.dist-info/RECORD
