Metadata-Version: 2.2
Name: countnclear
Version: 1.0.0
Summary: A package to count terminal executions and clear the terminal after a specified limit
Home-page: https://github.com/raxmatullox/CountNClear
Author: Raxmatullox
Author-email: raxmatulllox@icloud.com
Classifier: Programming Language :: Python :: 3
Classifier: License :: OSI Approved :: MIT License
Classifier: Operating System :: OS Independent
Requires-Python: >=3.6
License-File: LICENSE
Dynamic: author
Dynamic: author-email
Dynamic: classifier
Dynamic: description
Dynamic: description-content-type
Dynamic: home-page
Dynamic: requires-python
Dynamic: summary
